{
  "user": [
    {
      "id": 1,
      "user_id": "sjsjsj1246",
      "password": "123456",
      "author": "sjsjsj1246",
      "provider": "sjsjsj1246",
      "email": "sjsjsj1246@gmail.com",
      "coin_address": "0x23A486432C921453C",
      "woori_account": "374861327327186"
    }
  ],
  "products": [
    {
      "id": 1,
      "token_id": "sjsjsj1246",
      "owner_id": "sjsjsj1246",
      "author": "sjsjsj1246",
      "price": "10000",
      "is_action": true,
      "created_at": "20210429",
      "img": "https://lh3.googleusercontent.com/6Gwg5JlQkk95KRTYQ8MfQvVhxfx5MrP43RnAvA6X8GAcowkuMWJlAekeBmXLMpQ-iS-cWmnp_LRsowD2-XHSwt58w5BOYc6OxwM9Hw=s382",
      "title": "Buger",
      "tag": "Digital art",
      "star": 0
    },
    {
      "id": 2,
      "token_id": "sjsjsj1246",
      "owner_id": "sjsjsj1246",
      "author": "sjsjsj1246",
      "price": "10000",
      "is_action": true,
      "created_at": "20210429",
      "img": "https://lh3.googleusercontent.com/4LK2jwF0zccunZmiQF8wJfN_bzG9H2YvlR7qGlfL49Zz3NCOz1Y-QkCV3zV_mJXMD0FLpfRro9p-UDxYNZIg3uhGp7enzO12pgSlAg=s382",
      "title": "Buger",
      "tag": "Digital art",
      "star": 0
    }
  ],
  "action": [
    {
      "id": 1,
      "product_id": "sjsjsj1246",
      "user_id": "sjsjsj1246",
      "price": "10000",
      "created_at": "20210429"
    }
  ]
}
